localfiletransfer/__init__.py
localfiletransfer/server.py
localfiletransfer-0.1.0.dist-info/licenses/LICENSE
localfiletransfer-0.1.0.dist-info/METADATA
localfiletransfer-0.1.0.dist-info/WHEEL
localfiletransfer-0.1.0.dist-info/entry_points.txt
localfiletransfer-0.1.0.dist-info/top_level.txt
localfiletransfer-0.1.0.dist-info/RECORD
