Metadata-Version: 2.4
Name: localfiletransfer
Version: 0.1.0
Summary: A simple local network file transfer tool
Home-page: https://github.com/bivab0/localfiletransfer
Author: Bivab Das
Author-email: bivabdas@gmail.com
Classifier: Programming Language :: Python :: 3
Classifier: License :: OSI Approved :: MIT License
Classifier: Operating System :: OS Independent
Requires-Python: >=3.6
License-File: LICENSE
Requires-Dist: gunicorn
Dynamic: author
Dynamic: author-email
Dynamic: classifier
Dynamic: description
Dynamic: description-content-type
Dynamic: home-page
Dynamic: license-file
Dynamic: requires-dist
Dynamic: requires-python
Dynamic: summary
